.gitattributes
.readthedocs.yml
LICENSE
MANIFEST.in
README.md
pyproject.toml
requirements.txt
setup.py
src/NepTrain/__init__.py
src/NepTrain/config.ini
src/NepTrain/utils.py
src/NepTrain/cli/cli.py
src/NepTrain/core/__init__.py
src/NepTrain/core/template.py
src/NepTrain/core/utils.py
src/NepTrain/core/gpumd/__init__.py
src/NepTrain/core/gpumd/io.py
src/NepTrain/core/gpumd/plot.py
src/NepTrain/core/gpumd/run.in
src/NepTrain/core/gpumd/run.py
src/NepTrain/core/gpumd/utils.py
src/NepTrain/core/nep/__init__.py
src/NepTrain/core/nep/calculator.py
src/NepTrain/core/nep/io.py
src/NepTrain/core/nep/plot.py
src/NepTrain/core/nep/run.py
src/NepTrain/core/nep/utils.py
src/NepTrain/core/perturb/__init__.py
src/NepTrain/core/perturb/_hiphive.py
src/NepTrain/core/perturb/run.py
src/NepTrain/core/select/__init__.py
src/NepTrain/core/select/filter.py
src/NepTrain/core/select/run.py
src/NepTrain/core/select/select.py
src/NepTrain/core/train/__init__.py
src/NepTrain/core/train/job.yaml
src/NepTrain/core/train/run.py
src/NepTrain/core/train/worker.py
src/NepTrain/core/vasp/INCAR
src/NepTrain/core/vasp/__init__.py
src/NepTrain/core/vasp/io.py
src/NepTrain/core/vasp/run.py
src/NepTrain_ccmuyuu.egg-info/PKG-INFO
src/NepTrain_ccmuyuu.egg-info/SOURCES.txt
src/NepTrain_ccmuyuu.egg-info/dependency_links.txt
src/NepTrain_ccmuyuu.egg-info/entry_points.txt
src/NepTrain_ccmuyuu.egg-info/not-zip-safe
src/NepTrain_ccmuyuu.egg-info/requires.txt
src/NepTrain_ccmuyuu.egg-info/top_level.txt
src/nep_cpu/dftd3para.h
src/nep_cpu/nep.cpp
src/nep_cpu/nep.h
src/nep_cpu/nep_cpu.cpp